aws_cloudformation/__init__.py
aws_cloudformation/_version.py
aws_cloudformation/api.py
aws_cloudformation/change_set_visualizer.py
aws_cloudformation/compat.py
aws_cloudformation/deploy.py
aws_cloudformation/deploy_helpers.py
aws_cloudformation/exc.py
aws_cloudformation/helper.py
aws_cloudformation/stack.py
aws_cloudformation/stack_set.py
aws_cloudformation/taggings.py
aws_cloudformation/waiter.py
aws_cloudformation/better_boto/__init__.py
aws_cloudformation/better_boto/stacks.py
aws_cloudformation/better_boto/stacks_helpers.py
aws_cloudformation/better_boto/stacksets.py
aws_cloudformation/better_boto/stacksets_helpers.py
aws_cloudformation/docs/__init__.py
aws_cloudformation/tests/__init__.py
aws_cloudformation/tests/boto_ses.py
aws_cloudformation/tests/helper.py
aws_cloudformation/tests/mocker.py
aws_cloudformation/tests/paths.py
aws_cloudformation/tests/stacks/__init__.py
aws_cloudformation/tests/stacks/common.py
aws_cloudformation/tests/stacks/happy_path.py
aws_cloudformation/tests/stacks/iam_stack.py
aws_cloudformation/tests/stacks/malformed.py
aws_cloudformation/tests/stacks/secretmanager_stack.py
aws_cloudformation-1.5.1.dist-info/AUTHORS.rst
aws_cloudformation-1.5.1.dist-info/LICENSE.txt
aws_cloudformation-1.5.1.dist-info/METADATA
aws_cloudformation-1.5.1.dist-info/WHEEL
aws_cloudformation-1.5.1.dist-info/top_level.txt
aws_cloudformation-1.5.1.dist-info/RECORD
